imagedegrade/__init__.py
imagedegrade/im.py
imagedegrade/np.py
imagedegrade-0.2.3.dist-info/DESCRIPTION.rst
imagedegrade-0.2.3.dist-info/METADATA
imagedegrade-0.2.3.dist-info/RECORD
imagedegrade-0.2.3.dist-info/WHEEL
imagedegrade-0.2.3.dist-info/metadata.json
imagedegrade-0.2.3.dist-info/top_level.txt
tests/__init__.py
tests/test_imagedegrade.py
